infobot/__init__.py
infobot/brains.py
infobot/cli.py
infobot/config.py
infobot/index.py
infobot/konstants.py
infobot/social/__init__.py
infobot/social/fake.py
infobot/social/mastodon.py
infobot/social/template.py
infobot/storage/__init__.py
infobot/storage/coreguidelines.py
infobot/storage/file.py
infobot/storage/template.py
infobot/storage/test.py
infobot-0.3.0.dist-info/DESCRIPTION.rst
infobot-0.3.0.dist-info/METADATA
infobot-0.3.0.dist-info/RECORD
infobot-0.3.0.dist-info/WHEEL
infobot-0.3.0.dist-info/entry_points.txt
infobot-0.3.0.dist-info/metadata.json
infobot-0.3.0.dist-info/top_level.txt
