Metadata-Version: 2.0
Name: infobot
Version: 0.3.0
Summary: Infobot is an extensible social media posting bot.  It grabs candidate posts from a directory at random times and posts to different social media networks.
Home-page: https://github.com/otuk/infobot
Author: Otuk
Author-email: otuk@kodeten.com
License: MIT license
Keywords: infobot
Platform: UNKNOWN
Classifier: Development Status :: 3 - Alpha
Classifier: Intended Audience :: Developers
Classifier: License :: OSI Approved :: MIT License
Classifier: Natural Language :: English
Classifier: Programming Language :: Python :: 3
Classifier: Programming Language :: Python :: 3.4
Classifier: Programming Language :: Python :: 3.5
Classifier: Programming Language :: Python :: 3.6
Classifier: Programming Language :: Python :: 3.7
Requires-Dist: Click (>=6.0)
Requires-Dist: pyyaml
Requires-Dist: Mastodon.py
Requires-Dist: lxml
